pip_reqs/__init__.py
pip_reqs/__main__.py
pip_reqs/client.py
pip_reqs/compat.py
pip_reqs/conftest.py
pip_reqs/parser.py
pip_reqs/test/__init__.py
pip_reqs/test/test_client.py
pip_reqs/test/test_main.py
pip_reqs/test/test_parser.py
pip_reqs-0.12.0.dist-info/METADATA
pip_reqs-0.12.0.dist-info/WHEEL
pip_reqs-0.12.0.dist-info/entry_points.txt
pip_reqs-0.12.0.dist-info/top_level.txt
pip_reqs-0.12.0.dist-info/RECORD
