Metadata-Version: 2.1
Name: pip-reqs
Version: 0.12.0
Summary: Helpers for dealing with pip requirements
Home-page: https://divio.com
Author: Divio AG
Author-email: info@divio.com
License: MIT
Classifier: Development Status :: 4 - Beta
Classifier: Intended Audience :: Developers
Classifier: License :: OSI Approved :: MIT License
Classifier: Operating System :: OS Independent
Classifier: Programming Language :: Python
Classifier: Programming Language :: Python :: 3
Classifier: Programming Language :: Python :: 3.6
Classifier: Programming Language :: Python :: 3.7
